xkpa/__init__.py
xkpa/dict.txt
xkpa/xkpa.py
xkpa-0.1.4.dist-info/DESCRIPTION.rst
xkpa-0.1.4.dist-info/METADATA
xkpa-0.1.4.dist-info/RECORD
xkpa-0.1.4.dist-info/WHEEL
xkpa-0.1.4.dist-info/entry_points.txt
xkpa-0.1.4.dist-info/metadata.json
xkpa-0.1.4.dist-info/top_level.txt
