Metadata-Version: 2.0
Name: xkpa
Version: 0.1.4
Summary: A tool for generating xkcd style passwords.
Home-page: https://github.com/beala/xkcd-password
Author: Alex Beal
Author-email: alexlbeal@gmail.com
License: LICENSE.txt
Platform: UNKNOWN
Classifier: Topic :: Security
Classifier: Environment :: Console
Classifier: Development Status :: 5 - Production/Stable
Classifier: License :: OSI Approved :: MIT License
